maskilayer/__init__.py
maskilayer/__main__.py
maskilayer/maskilayer.py
maskilayer-1.0.6.dist-info/LICENSE.txt
maskilayer-1.0.6.dist-info/METADATA
maskilayer-1.0.6.dist-info/WHEEL
maskilayer-1.0.6.dist-info/entry_points.txt
maskilayer-1.0.6.dist-info/top_level.txt
maskilayer-1.0.6.dist-info/RECORD
